bios0032utils/__init__.py
bios0032utils/bioacoustics/.ipynb_checkpoints/evaluate_detection-checkpoint.py
bios0032utils/bioacoustics/__init__.py
bios0032utils/bioacoustics/audio.py
bios0032utils/bioacoustics/batdetect2.py
bios0032utils/bioacoustics/classification.py
bios0032utils/bioacoustics/detection.py
bios0032utils/bioacoustics/evaluate_detection.py
bios0032utils/bioacoustics/plotting.py
bios0032utils/vision/__init__.py
bios0032utils/vision/classification.py
bios0032utils/vision/datasets.py
bios0032utils/vision/detection.py
bios0032utils-0.1.1.dist-info/WHEEL
bios0032utils-0.1.1.dist-info/METADATA
bios0032utils-0.1.1.dist-info/licenses/LICENSE
bios0032utils-0.1.1.dist-info/RECORD
